README.md
setup.py
heiafr/hydrocontest/sensor_api/__init__.py
heiafr_hydrocontest_sensor_api.egg-info/PKG-INFO
heiafr_hydrocontest_sensor_api.egg-info/SOURCES.txt
heiafr_hydrocontest_sensor_api.egg-info/dependency_links.txt
heiafr_hydrocontest_sensor_api.egg-info/requires.txt
heiafr_hydrocontest_sensor_api.egg-info/top_level.txt